pyARSS/__init__.py
pyARSS/pyARSS.py
pyARSS-0.2.0.dist-info/LICENSE
pyARSS-0.2.0.dist-info/METADATA
pyARSS-0.2.0.dist-info/WHEEL
pyARSS-0.2.0.dist-info/top_level.txt
pyARSS-0.2.0.dist-info/RECORD
